JingtongTensorflow2XJisuanjiShijueChuyiFix1/README.md
JingtongTensorflow2XJisuanjiShijueChuyiFix1/__init__.py
JingtongTensorflow2XJisuanjiShijueChuyiFix1/__main__.py
JingtongTensorflow2XJisuanjiShijueChuyiFix1/file.epub
JingtongTensorflow2XJisuanjiShijueChuyiFix1/index.html
JingtongTensorflow2XJisuanjiShijueChuyiFix1/css/__init__.py
JingtongTensorflow2XJisuanjiShijueChuyiFix1/css/annotations.css
JingtongTensorflow2XJisuanjiShijueChuyiFix1/css/main.css
JingtongTensorflow2XJisuanjiShijueChuyiFix1/css/normalize.css
JingtongTensorflow2XJisuanjiShijueChuyiFix1/css/popup.css
JingtongTensorflow2XJisuanjiShijueChuyiFix1/font/__init__.py
JingtongTensorflow2XJisuanjiShijueChuyiFix1/font/fontello.eot
JingtongTensorflow2XJisuanjiShijueChuyiFix1/font/fontello.svg
JingtongTensorflow2XJisuanjiShijueChuyiFix1/font/fontello.ttf
JingtongTensorflow2XJisuanjiShijueChuyiFix1/font/fontello.woff
JingtongTensorflow2XJisuanjiShijueChuyiFix1/img/__init__.py
JingtongTensorflow2XJisuanjiShijueChuyiFix1/img/annotator-glyph-sprite.png
JingtongTensorflow2XJisuanjiShijueChuyiFix1/img/annotator-icon-sprite.png
JingtongTensorflow2XJisuanjiShijueChuyiFix1/img/apple-touch-icon.png
JingtongTensorflow2XJisuanjiShijueChuyiFix1/img/cancelfullscreen.png
JingtongTensorflow2XJisuanjiShijueChuyiFix1/img/close.png
JingtongTensorflow2XJisuanjiShijueChuyiFix1/img/fullscreen.png
JingtongTensorflow2XJisuanjiShijueChuyiFix1/img/loader.gif
JingtongTensorflow2XJisuanjiShijueChuyiFix1/img/menu-icon.png
JingtongTensorflow2XJisuanjiShijueChuyiFix1/img/save.png
JingtongTensorflow2XJisuanjiShijueChuyiFix1/img/saved.png
JingtongTensorflow2XJisuanjiShijueChuyiFix1/img/settings-s.png
JingtongTensorflow2XJisuanjiShijueChuyiFix1/img/settings.png
JingtongTensorflow2XJisuanjiShijueChuyiFix1/img/star.png
JingtongTensorflow2XJisuanjiShijueChuyiFix1/js/__init__.py
JingtongTensorflow2XJisuanjiShijueChuyiFix1/js/epub.js
JingtongTensorflow2XJisuanjiShijueChuyiFix1/js/epub.min.js
jingtong_tensorflow_2_x_jisuanji_shijue_chuyi_fix1-2025.3.25.1.dist-info/METADATA
jingtong_tensorflow_2_x_jisuanji_shijue_chuyi_fix1-2025.3.25.1.dist-info/WHEEL
jingtong_tensorflow_2_x_jisuanji_shijue_chuyi_fix1-2025.3.25.1.dist-info/entry_points.txt
jingtong_tensorflow_2_x_jisuanji_shijue_chuyi_fix1-2025.3.25.1.dist-info/top_level.txt
jingtong_tensorflow_2_x_jisuanji_shijue_chuyi_fix1-2025.3.25.1.dist-info/RECORD
